tscprojpy/__init__.py
tscprojpy/_version.py
tscprojpy/cli.py
tscprojpy/direct_scaler.py
tscprojpy/scaler.py
tscprojpy/models/__init__.py
tscprojpy/models/canvas.py
tscprojpy/models/factory.py
tscprojpy/models/media.py
tscprojpy/models/project.py
tscprojpy/models/source.py
tscprojpy/models/timeline.py
tscprojpy/serialization/__init__.py
tscprojpy/serialization/json_encoder.py
tscprojpy/serialization/loader.py
tscprojpy/serialization/saver.py
tscprojpy/serialization/version.py
tscprojpy/transforms/__init__.py
tscprojpy/transforms/engine.py
tscprojpy-1.0.2.dist-info/METADATA
tscprojpy-1.0.2.dist-info/WHEEL
tscprojpy-1.0.2.dist-info/entry_points.txt
tscprojpy-1.0.2.dist-info/RECORD
