Metadata-Version: 2.4
Name: tscprojpy
Version: 1.0.2
Summary: A modern Python project template
Project-URL: Homepage, https://github.com/twardoch/tscprojpy
Project-URL: Documentation, https://github.com/twardoch/tscprojpy
Project-URL: Repository, https://github.com/twardoch/tscprojpy
Project-URL: Issues, https://github.com/twardoch/tscprojpy/issues
Project-URL: Changelog, https://github.com/twardoch/tscprojpy/blob/main/CHANGELOG.md
Author-email: Adam Twardoch <adam+github@twardoch.com>
Maintainer-email: Adam Twardoch <adam+github@twardoch.com>
License: MIT
Classifier: Development Status :: 3 - Alpha
Classifier: Intended Audience :: Developers
Classifier: License :: OSI Approved :: MIT License
Classifier: Programming Language :: Python :: 3
Classifier: Programming Language :: Python :: 3.12
Classifier: Programming Language :: Python :: 3.13
Classifier: Programming Language :: Python :: 3.14
Requires-Python: >=3.12
Requires-Dist: fire>=0.7.0
Requires-Dist: loguru>=0.7.3
Requires-Dist: rich>=13.0.0
Provides-Extra: dev
Requires-Dist: build>=1.0.0; extra == 'dev'
Requires-Dist: pytest-cov>=4.1.0; extra == 'dev'
Requires-Dist: pytest>=7.4.0; extra == 'dev'
Requires-Dist: ruff>=0.1.0; extra == 'dev'
Requires-Dist: twine>=4.0.0; extra == 'dev'
